<root schemeVersion="1.0.4" direction="ltr"><unitGroups><unit type="Process" id="850" unanalyzable="false" uncertain="false"></unit><unit type="Parallel Scene" id="747" unanalyzable="false" uncertain="false"></unit><unit type="Process" id="743" unanalyzable="false" uncertain="false"></unit><unit type="Linker" id="771" unanalyzable="true" uncertain="false"></unit><unit type="Parallel Scene" id="768" unanalyzable="false" uncertain="false"></unit><unit type="Process" id="817" unanalyzable="false" uncertain="false"></unit><unit type="Process" id="921" unanalyzable="false" uncertain="false"></unit><unit type="Process" id="940" unanalyzable="false" uncertain="false"></unit><unit type="Parallel Scene" id="1144" unanalyzable="false" uncertain="false"></unit><unit type="Process" id="1063" unanalyzable="false" uncertain="false"></unit><unit type="Process" id="1076" unanalyzable="false" uncertain="false"></unit></unitGroups><units passageID="113"><unit type="To Be Defined" id="0" unanalyzable="false" uncertain="false"><unit type="To Be Defined" id="1" unanalyzable="false" uncertain="false"><unit type="Parallel Scene" id="690" unanalyzable="false" uncertain="false"><unit type="Participant" id="689" unanalyzable="false" uncertain="false"><unit type="Participant" id="644" unanalyzable="false" uncertain="false"><unit type="Elaborator" id="658" unanalyzable="false" uncertain="false"><unit type="To Be Defined" id="849" unitGroupID="850" unanalyzable="false" uncertain="false"><unit type="Elaborator" id="654" unanalyzable="false" uncertain="false"><unit type="To Be Defined" id="3" unanalyzable="false" uncertain="false"><word id="2">A</word></unit></unit></unit><unit type="Participant" id="655" unanalyzable="false" uncertain="false"><unit type="To Be Defined" id="5" unanalyzable="false" uncertain="false"><word id="4">SEC</word></unit></unit><unit type="To Be Defined" id="851" unitGroupID="850" unanalyzable="false" uncertain="false"><unit type="Center" id="656" unanalyzable="false" uncertain="false"><unit type="To Be Defined" id="7" unanalyzable="false" uncertain="false"><word id="6">proposal</word></unit></unit></unit></unit><unit type="Center" id="657" unanalyzable="false" uncertain="false"><unit type="Process" id="651" unanalyzable="false" uncertain="false"><unit type="Function" id="652" unanalyzable="false" uncertain="false"><unit type="To Be Defined" id="9" unanalyzable="false" uncertain="false"><word id="8">to</word></unit></unit><unit type="Center" id="653" unanalyzable="false" uncertain="false"><unit type="To Be Defined" id="11" unanalyzable="false" uncertain="false"><word id="10">ease</word></unit></unit></unit><unit type="Participant" id="1129" unanalyzable="false" uncertain="false"><unit type="Elaborator" id="659" unanalyzable="false" uncertain="false"><unit type="To Be Defined" id="13" unanalyzable="false" uncertain="false"><word id="12">reporting</word></unit></unit><unit type="Center" id="660" unanalyzable="false" uncertain="false"><unit type="To Be Defined" id="15" unanalyzable="false" uncertain="false"><word id="14">requirements</word></unit></unit><unit type="Elaborator" id="650" unanalyzable="false" uncertain="false"><unit type="Relator" id="661" unanalyzable="false" uncertain="false"><unit type="To Be Defined" id="17" unanalyzable="false" uncertain="false"><word id="16">for</word></unit></unit><unit type="Elaborator" id="662" unanalyzable="false" uncertain="false"><unit type="To Be Defined" id="19" unanalyzable="false" uncertain="false"><word id="18">some</word></unit></unit><unit type="Elaborator" id="663" unanalyzable="false" uncertain="false"><unit type="To Be Defined" id="21" unanalyzable="false" uncertain="false"><word id="20">company</word></unit></unit><unit type="Center" id="664" unanalyzable="false" uncertain="false"><unit type="To Be Defined" id="23" unanalyzable="false" uncertain="false"><word id="22">executives</word></unit></unit></unit></unit></unit></unit><unit type="Process" id="645" unanalyzable="false" uncertain="false"><unit type="Elaborator" id="665" unanalyzable="false" uncertain="false"><unit type="To Be Defined" id="25" unanalyzable="false" uncertain="false"><word id="24">would</word></unit></unit><unit type="Center" id="666" unanalyzable="false" uncertain="false"><unit type="To Be Defined" id="27" unanalyzable="false" uncertain="false"><word id="26">undermine</word></unit></unit></unit><unit type="Participant" id="646" unanalyzable="false" uncertain="false"><unit type="State" id="852" unanalyzable="false" uncertain="false"><unit type="Elaborator" id="667" unanalyzable="false" uncertain="false"><unit type="To Be Defined" id="29" unanalyzable="false" uncertain="false"><word id="28">the</word></unit></unit><unit type="Center" id="668" unanalyzable="false" uncertain="false"><unit type="To Be Defined" id="31" unanalyzable="false" uncertain="false"><word id="30">usefulness</word></unit></unit></unit><unit type="Participant" id="853" unanalyzable="false" uncertain="false"><unit type="Relator" id="670" unanalyzable="false" uncertain="false"><unit type="To Be Defined" id="33" unanalyzable="false" uncertain="false"><word id="32">of</word></unit></unit><unit type="Center" id="671" unanalyzable="false" uncertain="false"><unit type="To Be Defined" id="35" unanalyzable="false" uncertain="false"><word id="34">information</word></unit></unit><unit type="Elaborator" id="854" unanalyzable="false" uncertain="false"><unit type="Relator" id="673" unanalyzable="false" uncertain="false"><unit type="To Be Defined" id="37" unanalyzable="false" uncertain="false"><word id="36">on</word></unit></unit><unit type="Elaborator" id="674" unanalyzable="false" uncertain="false"><unit type="To Be Defined" id="39" unanalyzable="false" uncertain="false"><word id="38">insider</word></unit></unit><unit type="Center" id="675" unanalyzable="false" uncertain="false"><unit type="To Be Defined" id="41" unanalyzable="false" uncertain="false"><word id="40">trades</word></unit></unit></unit></unit><unit type="Participant" id="676" unanalyzable="false" uncertain="false"><unit type="Relator" id="677" unanalyzable="false" uncertain="false"><unit type="To Be Defined" id="43" unanalyzable="false" uncertain="false"><word id="42">as</word></unit></unit><unit type="Elaborator" id="678" unanalyzable="false" uncertain="false"><unit type="To Be Defined" id="45" unanalyzable="false" uncertain="false"><word id="44">a</word></unit></unit><unit type="Elaborator" id="679" unanalyzable="false" uncertain="false"><unit type="To Be Defined" id="47" unanalyzable="false" uncertain="false"><word id="46">stock-picking</word></unit></unit><unit type="Center" id="680" unanalyzable="false" uncertain="false"><unit type="To Be Defined" id="49" unanalyzable="false" uncertain="false"><word id="48">tool</word></unit></unit></unit></unit></unit><unit type="Punctuation" id="51" unanalyzable="false" uncertain="false"><word id="50">,</word></unit><unit type="Participant" id="647" unanalyzable="false" uncertain="false"><unit type="Center" id="681" unanalyzable="false" uncertain="false"><unit type="Elaborator" id="684" unanalyzable="false" uncertain="false"><unit type="To Be Defined" id="53" unanalyzable="false" uncertain="false"><word id="52">individual</word></unit></unit><unit type="Center" id="685" unanalyzable="false" uncertain="false"><unit type="To Be Defined" id="55" unanalyzable="false" uncertain="false"><word id="54">investors</word></unit></unit></unit><unit type="Connector" id="682" unanalyzable="false" uncertain="false"><unit type="To Be Defined" id="57" unanalyzable="false" uncertain="false"><word id="56">and</word></unit></unit><unit type="Center" id="683" unanalyzable="false" uncertain="false"><unit type="Elaborator" id="686" unanalyzable="false" uncertain="false"><unit type="To Be Defined" id="59" unanalyzable="false" uncertain="false"><word id="58">professional</word></unit></unit><unit type="Elaborator" id="687" unanalyzable="false" uncertain="false"><unit type="To Be Defined" id="61" unanalyzable="false" uncertain="false"><word id="60">money</word></unit></unit><unit type="Center" id="688" unanalyzable="false" uncertain="false"><unit type="To Be Defined" id="63" unanalyzable="false" uncertain="false"><word id="62">managers</word></unit></unit></unit></unit><unit type="Process" id="648" unanalyzable="false" uncertain="false"><unit type="To Be Defined" id="65" unanalyzable="false" uncertain="false"><word id="64">contend</word></unit></unit></unit><unit type="Punctuation" id="67" unanalyzable="false" uncertain="false"><word id="66">.</word></unit><unit type="Parallel Scene" id="703" unanalyzable="false" uncertain="false"><unit type="Participant" id="691" unanalyzable="false" uncertain="false"><unit type="To Be Defined" id="69" unanalyzable="false" uncertain="false"><word id="68">They</word></unit></unit><unit type="Process" id="692" unanalyzable="false" uncertain="false"><unit type="Function" id="693" unanalyzable="false" uncertain="false"><unit type="To Be Defined" id="71" unanalyzable="false" uncertain="false"><word id="70">make</word></unit></unit><unit type="Center" id="694" unanalyzable="false" uncertain="false"><unit type="Elaborator" id="695" unanalyzable="false" uncertain="false"><unit type="To Be Defined" id="73" unanalyzable="false" uncertain="false"><word id="72">the</word></unit></unit><unit type="Center" id="696" unanalyzable="false" uncertain="false"><unit type="To Be Defined" id="75" unanalyzable="false" uncertain="false"><word id="74">argument</word></unit></unit></unit></unit><unit type="Participant" id="1130" unanalyzable="false" uncertain="false"><unit type="Relator" id="698" unanalyzable="false" uncertain="false"><unit type="To Be Defined" id="77" unanalyzable="false" uncertain="false"><word id="76">in</word></unit></unit><unit type="Center" id="699" unanalyzable="false" uncertain="false"><unit type="To Be Defined" id="79" unanalyzable="false" uncertain="false"><word id="78">letters</word></unit></unit><unit type="Elaborator" id="700" unanalyzable="false" uncertain="false"><unit type="Relator" id="896" unanalyzable="false" uncertain="false"><unit type="To Be Defined" id="81" unanalyzable="false" uncertain="false"><word id="80">to</word></unit></unit><unit type="Elaborator" id="897" unanalyzable="false" uncertain="false"><unit type="To Be Defined" id="83" unanalyzable="false" uncertain="false"><word id="82">the</word></unit></unit><unit type="Center" id="898" unanalyzable="false" uncertain="false"><unit type="To Be Defined" id="85" unanalyzable="false" uncertain="false"><word id="84">agency</word></unit></unit></unit><unit type="Elaborator" id="701" unanalyzable="false" uncertain="false"><unit type="Relator" id="855" unanalyzable="false" uncertain="false"><unit type="To Be Defined" id="87" unanalyzable="false" uncertain="false"><word id="86">about</word></unit></unit><unit type="Elaborator" id="856" unanalyzable="false" uncertain="false"><unit type="To Be Defined" id="89" unanalyzable="false" uncertain="false"><word id="88">rule</word></unit></unit><unit type="Center" id="857" unanalyzable="false" uncertain="false"><unit type="To Be Defined" id="91" unanalyzable="false" uncertain="false"><word id="90">changes</word></unit></unit><unit type="Elaborator" id="861" unanalyzable="false" uncertain="false"><remoteUnit id="857" type="Participant"></remoteUnit><unit type="Process" id="859" unanalyzable="false" uncertain="false"><unit type="To Be Defined" id="93" unanalyzable="false" uncertain="false"><word id="92">proposed</word></unit></unit><unit type="aDverbial" id="860" unanalyzable="false" uncertain="false"><unit type="Elaborator" id="863" unanalyzable="false" uncertain="false"><unit type="To Be Defined" id="95" unanalyzable="false" uncertain="false"><word id="94">this</word></unit></unit><unit type="Elaborator" id="864" unanalyzable="false" uncertain="false"><unit type="To Be Defined" id="97" unanalyzable="false" uncertain="false"><word id="96">past</word></unit></unit><unit type="Center" id="865" unanalyzable="false" uncertain="false"><unit type="To Be Defined" id="99" unanalyzable="false" uncertain="false"><word id="98">summer</word></unit></unit></unit></unit><unit type="Elaborator" id="862" unanalyzable="false" uncertain="false"><remoteUnit id="857" type="Participant"></remoteUnit><unit type="Relator" id="866" unanalyzable="false" uncertain="false"><unit type="To Be Defined" id="101" unanalyzable="false" uncertain="false"><word id="100">that</word></unit></unit><unit type="Punctuation" id="103" unanalyzable="false" uncertain="false"><word id="102">,</word></unit><unit type="Participant" id="867" unanalyzable="false" uncertain="false"><unit type="Connector" id="874" unanalyzable="false" uncertain="false"><unit type="To Be Defined" id="105" unanalyzable="false" uncertain="false"><word id="104">among</word></unit></unit><unit type="Center" id="875" unanalyzable="false" uncertain="false"><unit type="Elaborator" id="876" unanalyzable="false" uncertain="false"><unit type="To Be Defined" id="107" unanalyzable="false" uncertain="false"><word id="106">other</word></unit></unit><unit type="Center" id="877" unanalyzable="false" uncertain="false"><unit type="To Be Defined" id="109" unanalyzable="false" uncertain="false"><word id="108">things</word></unit></unit></unit></unit><unit type="Punctuation" id="111" unanalyzable="false" uncertain="false"><word id="110">,</word></unit><unit type="Process" id="868" unanalyzable="false" uncertain="false"><unit type="Elaborator" id="878" unanalyzable="false" uncertain="false"><unit type="To Be Defined" id="113" unanalyzable="false" uncertain="false"><word id="112">would</word></unit></unit><unit type="Center" id="879" unanalyzable="false" uncertain="false"><unit type="To Be Defined" id="115" unanalyzable="false" uncertain="false"><word id="114">exempt</word></unit></unit></unit><unit type="Participant" id="869" unanalyzable="false" uncertain="false"><unit type="Elaborator" id="880" unanalyzable="false" uncertain="false"><unit type="To Be Defined" id="117" unanalyzable="false" uncertain="false"><word id="116">many</word></unit></unit><unit type="Elaborator" id="881" unanalyzable="false" uncertain="false"><unit type="To Be Defined" id="119" unanalyzable="false" uncertain="false"><word id="118">middle-management</word></unit></unit><unit type="Center" id="882" unanalyzable="false" uncertain="false"><unit type="To Be Defined" id="121" unanalyzable="false" uncertain="false"><word id="120">executives</word></unit></unit></unit><unit type="Participant" id="871" unanalyzable="false" uncertain="false"><remoteUnit id="869" type="Participant"></remoteUnit><unit type="Relator" id="883" unanalyzable="false" uncertain="false"><unit type="To Be Defined" id="123" unanalyzable="false" uncertain="false"><word id="122">from</word></unit></unit><unit type="Process" id="884" unanalyzable="false" uncertain="false"><unit type="To Be Defined" id="125" unanalyzable="false" uncertain="false"><word id="124">reporting</word></unit></unit><unit type="Participant" id="1134" unanalyzable="false" uncertain="false"><unit type="Center" id="1136" unanalyzable="false" uncertain="false"><unit type="To Be Defined" id="127" unanalyzable="false" uncertain="false"><word id="126">trades</word></unit></unit><unit type="Elaborator" id="1135" unanalyzable="false" uncertain="false"><unit type="Relator" id="887" unanalyzable="false" uncertain="false"><unit type="To Be Defined" id="129" unanalyzable="false" uncertain="false"><word id="128">in</word></unit></unit><unit type="Elaborator" id="890" unanalyzable="false" uncertain="false"><unit type="Elaborator" id="893" unanalyzable="false" uncertain="false"><unit type="Center" id="895" unanalyzable="false" uncertain="false"><unit type="To Be Defined" id="131" unanalyzable="false" uncertain="false"><word id="130">their</word></unit></unit><unit type="Function" id="894" unanalyzable="false" uncertain="false"><unit type="To Be Defined" id="133" unanalyzable="false" uncertain="false"><word id="132">own</word></unit></unit></unit><unit type="Center" id="892" unanalyzable="false" uncertain="false"><unit type="To Be Defined" id="135" unanalyzable="false" uncertain="false"><word id="134">companies</word></unit></unit></unit><unit type="Punctuation" id="137" unanalyzable="false" uncertain="false"><word id="136">'</word></unit><unit type="Center" id="891" unanalyzable="false" uncertain="false"><unit type="To Be Defined" id="139" unanalyzable="false" uncertain="false"><word id="138">shares</word></unit></unit></unit></unit></unit></unit></unit></unit></unit><unit type="Punctuation" id="141" unanalyzable="false" uncertain="false"><word id="140">.</word></unit><unit type="Parallel Scene" id="710" unanalyzable="false" uncertain="false"><unit type="Participant" id="704" unanalyzable="false" uncertain="false"><unit type="Elaborator" id="711" unanalyzable="false" uncertain="false"><unit type="To Be Defined" id="143" unanalyzable="false" uncertain="false"><word id="142">The</word></unit></unit><unit type="Elaborator" id="712" unanalyzable="false" uncertain="false"><unit type="To Be Defined" id="145" unanalyzable="false" uncertain="false"><word id="144">proposed</word></unit></unit><unit type="Center" id="713" unanalyzable="false" uncertain="false"><unit type="To Be Defined" id="147" unanalyzable="false" uncertain="false"><word id="146">changes</word></unit></unit></unit><unit type="aDverbial" id="705" unanalyzable="false" uncertain="false"><unit type="To Be Defined" id="149" unanalyzable="false" uncertain="false"><word id="148">also</word></unit></unit><unit type="Process" id="708" unanalyzable="false" uncertain="false"><unit type="Elaborator" id="714" unanalyzable="false" uncertain="false"><unit type="To Be Defined" id="151" unanalyzable="false" uncertain="false"><word id="150">would</word></unit></unit><unit type="Center" id="715" unanalyzable="false" uncertain="false"><unit type="To Be Defined" id="153" unanalyzable="false" uncertain="false"><word id="152">allow</word></unit></unit></unit><unit type="Participant" id="1137" unanalyzable="false" uncertain="false"><unit type="Center" id="707" unanalyzable="false" uncertain="false"><unit type="To Be Defined" id="155" unanalyzable="false" uncertain="false"><word id="154">executives</word></unit></unit><unit type="Elaborator" id="709" unanalyzable="false" uncertain="false"><remoteUnit id="707" type="Participant"></remoteUnit><unit type="Process" id="716" unanalyzable="false" uncertain="false"><unit type="Function" id="725" unanalyzable="false" uncertain="false"><unit type="To Be Defined" id="157" unanalyzable="false" uncertain="false"><word id="156">to</word></unit></unit><unit type="Center" id="726" unanalyzable="false" uncertain="false"><unit type="To Be Defined" id="159" unanalyzable="false" uncertain="false"><word id="158">report</word></unit></unit></unit><unit type="Participant" id="718" unanalyzable="false" uncertain="false"><remoteUnit id="707" type="Participant"></remoteUnit><unit type="Process" id="727" unanalyzable="false" uncertain="false"><unit type="To Be Defined" id="161" unanalyzable="false" uncertain="false"><word id="160">exercises</word></unit></unit><unit type="Participant" id="728" unanalyzable="false" uncertain="false"><unit type="Relator" id="729" unanalyzable="false" uncertain="false"><unit type="To Be Defined" id="163" unanalyzable="false" uncertain="false"><word id="162">of</word></unit></unit><unit type="Center" id="730" unanalyzable="false" uncertain="false"><unit type="To Be Defined" id="165" unanalyzable="false" uncertain="false"><word id="164">options</word></unit></unit></unit></unit><unit type="aDverbial" id="720" unanalyzable="false" uncertain="false"><unit type="Center" id="719" unanalyzable="false" uncertain="false"><unit type="To Be Defined" id="167" unanalyzable="false" uncertain="false"><word id="166">later</word></unit></unit><unit type="Connector" id="721" unanalyzable="false" uncertain="false"><unit type="To Be Defined" id="169" unanalyzable="false" uncertain="false"><word id="168">and</word></unit></unit><unit type="Center" id="722" unanalyzable="false" uncertain="false"><unit type="Elaborator" id="723" unanalyzable="false" uncertain="false"><unit type="To Be Defined" id="171" unanalyzable="false" uncertain="false"><word id="170">less</word></unit></unit><unit type="Center" id="724" unanalyzable="false" uncertain="false"><unit type="To Be Defined" id="173" unanalyzable="false" uncertain="false"><word id="172">often</word></unit></unit></unit></unit></unit></unit></unit><unit type="Punctuation" id="175" unanalyzable="false" uncertain="false"><word id="174">.</word></unit><unit type="Parallel Scene" id="731" unanalyzable="false" uncertain="false"><unit type="Participant" id="732" unanalyzable="false" uncertain="false"><unit type="Elaborator" id="736" unanalyzable="false" uncertain="false"><unit type="Center" id="739" unanalyzable="false" uncertain="false"><unit type="To Be Defined" id="177" unanalyzable="false" uncertain="false"><word id="176">Many</word></unit></unit><unit type="Relator" id="740" unanalyzable="false" uncertain="false"><unit type="To Be Defined" id="179" unanalyzable="false" uncertain="false"><word id="178">of</word></unit></unit></unit><unit type="Elaborator" id="737" unanalyzable="false" uncertain="false"><unit type="To Be Defined" id="181" unanalyzable="false" uncertain="false"><word id="180">the</word></unit></unit><unit type="Center" id="738" unanalyzable="false" uncertain="false"><unit type="To Be Defined" id="183" unanalyzable="false" uncertain="false"><word id="182">letters</word></unit></unit></unit><unit type="Process" id="733" unanalyzable="false" uncertain="false"><unit type="To Be Defined" id="185" unanalyzable="false" uncertain="false"><word id="184">maintain</word></unit></unit><unit type="Participant" id="734" unanalyzable="false" uncertain="false"><unit type="Relator" id="735" unanalyzable="false" uncertain="false"><unit type="To Be Defined" id="187" unanalyzable="false" uncertain="false"><word id="186">that</word></unit></unit><unit type="To Be Defined" id="746" unitGroupID="747" unanalyzable="false" uncertain="false"><unit type="Participant" id="741" unanalyzable="false" uncertain="false"><unit type="Elaborator" id="755" unanalyzable="false" uncertain="false"><unit type="To Be Defined" id="189" unanalyzable="false" uncertain="false"><word id="188">investor</word></unit></unit><unit type="Center" id="756" unanalyzable="false" uncertain="false"><unit type="To Be Defined" id="191" unanalyzable="false" uncertain="false"><word id="190">confidence</word></unit></unit></unit><unit type="To Be Defined" id="742" unitGroupID="743" unanalyzable="false" uncertain="false"><unit type="Function" id="757" unanalyzable="false" uncertain="false"><unit type="To Be Defined" id="193" unanalyzable="false" uncertain="false"><word id="192">has</word></unit></unit><unit type="Function" id="758" unanalyzable="false" uncertain="false"><unit type="To Be Defined" id="195" unanalyzable="false" uncertain="false"><word id="194">been</word></unit></unit></unit></unit><unit type="To Be Defined" id="770" unitGroupID="771" unanalyzable="false" uncertain="false"><unit type="To Be Defined" id="197" unanalyzable="false" uncertain="false"><word id="196">so</word></unit></unit><unit type="To Be Defined" id="748" unitGroupID="747" unanalyzable="false" uncertain="false"><unit type="To Be Defined" id="744" unitGroupID="743" unanalyzable="false" uncertain="false"><unit type="Center" id="759" unanalyzable="false" uncertain="false"><unit type="To Be Defined" id="199" unanalyzable="false" uncertain="false"><word id="198">shaken</word></unit></unit></unit><unit type="Participant" id="745" unanalyzable="false" uncertain="false"><unit type="Relator" id="760" unanalyzable="false" uncertain="false"><unit type="To Be Defined" id="201" unanalyzable="false" uncertain="false"><word id="200">by</word></unit></unit><unit type="Elaborator" id="761" unanalyzable="false" uncertain="false"><unit type="To Be Defined" id="203" unanalyzable="false" uncertain="false"><word id="202">the</word></unit></unit><unit type="Elaborator" id="762" unanalyzable="false" uncertain="false"><unit type="To Be Defined" id="205" unanalyzable="false" uncertain="false"><word id="204">1987</word></unit></unit><unit type="Elaborator" id="764" unanalyzable="false" uncertain="false"><unit type="Elaborator" id="763" unanalyzable="false" uncertain="false"><unit type="To Be Defined" id="207" unanalyzable="false" uncertain="false"><word id="206">stock</word></unit></unit><unit type="Center" id="766" unanalyzable="false" uncertain="false"><unit type="To Be Defined" id="209" unanalyzable="false" uncertain="false"><word id="208">market</word></unit></unit></unit><unit type="Center" id="765" unanalyzable="false" uncertain="false"><unit type="To Be Defined" id="211" unanalyzable="false" uncertain="false"><word id="210">crash</word></unit></unit></unit></unit><unit type="Punctuation" id="213" unanalyzable="false" uncertain="false"><word id="212">--</word></unit><unit type="Linker" id="749" unanalyzable="false" uncertain="false"><unit type="To Be Defined" id="215" unanalyzable="false" uncertain="false"><word id="214">and</word></unit></unit><unit type="To Be Defined" id="767" unitGroupID="768" unanalyzable="false" uncertain="false"><unit type="Participant" id="774" unanalyzable="false" uncertain="false"><unit type="Elaborator" id="778" unanalyzable="false" uncertain="false"><unit type="To Be Defined" id="217" unanalyzable="false" uncertain="false"><word id="216">the</word></unit></unit><unit type="Center" id="779" unanalyzable="false" uncertain="false"><unit type="To Be Defined" id="219" unanalyzable="false" uncertain="false"><word id="218">markets</word></unit></unit></unit><unit type="aDverbial" id="775" unanalyzable="false" uncertain="false"><unit type="To Be Defined" id="221" unanalyzable="false" uncertain="false"><word id="220">already</word></unit></unit></unit><unit type="To Be Defined" id="772" unitGroupID="771" unanalyzable="false" uncertain="false"><unit type="To Be Defined" id="223" unanalyzable="false" uncertain="false"><word id="222">so</word></unit></unit><unit type="To Be Defined" id="769" unitGroupID="768" unanalyzable="false" uncertain="false"><unit type="Process" id="776" unanalyzable="false" uncertain="false"><unit type="To Be Defined" id="225" unanalyzable="false" uncertain="false"><word id="224">stacked</word></unit></unit><unit type="Participant" id="782" unanalyzable="false" uncertain="false"><unit type="Relator" id="780" unanalyzable="false" uncertain="false"><unit type="To Be Defined" id="227" unanalyzable="false" uncertain="false"><word id="226">against</word></unit></unit><unit type="Elaborator" id="781" unanalyzable="false" uncertain="false"><unit type="To Be Defined" id="229" unanalyzable="false" uncertain="false"><word id="228">the</word></unit></unit><unit type="Elaborator" id="784" unanalyzable="false" uncertain="false"><unit type="To Be Defined" id="231" unanalyzable="false" uncertain="false"><word id="230">little</word></unit></unit><unit type="Center" id="783" unanalyzable="false" uncertain="false"><unit type="To Be Defined" id="233" unanalyzable="false" uncertain="false"><word id="232">guy</word></unit></unit></unit></unit><unit type="Punctuation" id="235" unanalyzable="false" uncertain="false"><word id="234">--</word></unit><unit type="To Be Defined" id="773" unitGroupID="771" unanalyzable="false" uncertain="false"><unit type="To Be Defined" id="237" unanalyzable="false" uncertain="false"><word id="236">that</word></unit></unit><unit type="Parallel Scene" id="754" unanalyzable="false" uncertain="false"><unit type="Participant" id="785" unanalyzable="false" uncertain="false"><unit type="Elaborator" id="800" unanalyzable="false" uncertain="false"><unit type="To Be Defined" id="239" unanalyzable="false" uncertain="false"><word id="238">any</word></unit></unit><unit type="Center" id="801" unanalyzable="false" uncertain="false"><unit type="Process" id="802" unanalyzable="false" uncertain="false"><unit type="To Be Defined" id="241" unanalyzable="false" uncertain="false"><word id="240">decrease</word></unit></unit><unit type="Participant" id="803" unanalyzable="false" uncertain="false"><unit type="Relator" id="804" unanalyzable="false" uncertain="false"><unit type="To Be Defined" id="243" unanalyzable="false" uncertain="false"><word id="242">in</word></unit></unit><unit type="Center" id="805" unanalyzable="false" uncertain="false"><unit type="To Be Defined" id="245" unanalyzable="false" uncertain="false"><word id="244">information</word></unit></unit><unit type="Elaborator" id="806" unanalyzable="false" uncertain="false"><unit type="Relator" id="807" unanalyzable="false" uncertain="false"><unit type="To Be Defined" id="247" unanalyzable="false" uncertain="false"><word id="246">on</word></unit></unit><unit type="Elaborator" id="808" unanalyzable="false" uncertain="false"><unit type="To Be Defined" id="249" unanalyzable="false" uncertain="false"><word id="248">insider-trading</word></unit></unit><unit type="Center" id="809" unanalyzable="false" uncertain="false"><unit type="To Be Defined" id="251" unanalyzable="false" uncertain="false"><word id="250">patterns</word></unit></unit></unit></unit></unit></unit><unit type="Process" id="786" unanalyzable="false" uncertain="false"><unit type="Elaborator" id="798" unanalyzable="false" uncertain="false"><unit type="To Be Defined" id="253" unanalyzable="false" uncertain="false"><word id="252">might</word></unit></unit><unit type="Center" id="799" unanalyzable="false" uncertain="false"><unit type="To Be Defined" id="255" unanalyzable="false" uncertain="false"><word id="254">prompt</word></unit></unit></unit><unit type="Participant" id="787" unanalyzable="false" uncertain="false"><unit type="To Be Defined" id="257" unanalyzable="false" uncertain="false"><word id="256">individuals</word></unit></unit><unit type="Participant" id="788" unanalyzable="false" uncertain="false"><remoteUnit id="787" type="Participant"></remoteUnit><unit type="Process" id="790" unanalyzable="false" uncertain="false"><unit type="Function" id="794" unanalyzable="false" uncertain="false"><unit type="To Be Defined" id="259" unanalyzable="false" uncertain="false"><word id="258">to</word></unit></unit><unit type="Center" id="795" unanalyzable="true" uncertain="false"><unit type="To Be Defined" id="261" unanalyzable="false" uncertain="false"><word id="260">get</word></unit><unit type="To Be Defined" id="263" unanalyzable="false" uncertain="false"><word id="262">out</word></unit></unit></unit><unit type="Participant" id="791" unanalyzable="false" uncertain="false"><unit type="Relator" id="796" unanalyzable="false" uncertain="false"><unit type="To Be Defined" id="265" unanalyzable="false" uncertain="false"><word id="264">of</word></unit></unit><unit type="Center" id="797" unanalyzable="false" uncertain="false"><unit type="To Be Defined" id="267" unanalyzable="false" uncertain="false"><word id="266">stocks</word></unit></unit></unit><unit type="aDverbial" id="792" unanalyzable="false" uncertain="false"><unit type="To Be Defined" id="269" unanalyzable="false" uncertain="false"><word id="268">altogether</word></unit></unit></unit></unit></unit></unit><unit type="Punctuation" id="271" unanalyzable="false" uncertain="false"><word id="270">.</word></unit><unit type="Punctuation" id="273" unanalyzable="false" uncertain="false"><word id="272">``</word></unit><unit type="Parallel Scene" id="810" unanalyzable="false" uncertain="false"><unit type="Participant" id="820" unanalyzable="false" uncertain="false"><unit type="Participant" id="811" unanalyzable="false" uncertain="false"><unit type="Elaborator" id="902" unanalyzable="false" uncertain="false"><unit type="To Be Defined" id="275" unanalyzable="false" uncertain="false"><word id="274">The</word></unit></unit><unit type="Center" id="903" unanalyzable="false" uncertain="false"><unit type="To Be Defined" id="277" unanalyzable="false" uncertain="false"><word id="276">SEC</word></unit></unit></unit><unit type="To Be Defined" id="816" unitGroupID="817" unanalyzable="false" uncertain="false"><unit type="Function" id="899" unanalyzable="false" uncertain="false"><unit type="To Be Defined" id="279" unanalyzable="false" uncertain="false"><word id="278">has</word></unit></unit></unit><unit type="aDverbial" id="815" unanalyzable="false" uncertain="false"><unit type="To Be Defined" id="281" unanalyzable="false" uncertain="false"><word id="280">historically</word></unit></unit><unit type="To Be Defined" id="818" unitGroupID="817" unanalyzable="false" uncertain="false"><unit type="Function" id="901" unanalyzable="false" uncertain="false"><unit type="To Be Defined" id="283" unanalyzable="false" uncertain="false"><word id="282">paid</word></unit></unit><unit type="Center" id="900" unanalyzable="false" uncertain="false"><unit type="To Be Defined" id="285" unanalyzable="false" uncertain="false"><word id="284">obeisance</word></unit></unit></unit><unit type="Participant" id="819" unanalyzable="false" uncertain="false"><unit type="Relator" id="904" unanalyzable="false" uncertain="false"><unit type="To Be Defined" id="287" unanalyzable="false" uncertain="false"><word id="286">to</word></unit></unit><unit type="Elaborator" id="905" unanalyzable="false" uncertain="false"><unit type="To Be Defined" id="289" unanalyzable="false" uncertain="false"><word id="288">the</word></unit></unit><unit type="Center" id="917" unanalyzable="false" uncertain="false"><unit type="Center" id="906" unanalyzable="false" uncertain="false"><unit type="To Be Defined" id="291" unanalyzable="false" uncertain="false"><word id="290">ideal</word></unit></unit><unit type="Relator" id="908" unanalyzable="false" uncertain="false"><unit type="To Be Defined" id="293" unanalyzable="false" uncertain="false"><word id="292">of</word></unit></unit><unit type="Center" id="915" unanalyzable="false" uncertain="false"><unit type="Elaborator" id="909" unanalyzable="false" uncertain="false"><unit type="To Be Defined" id="295" unanalyzable="false" uncertain="false"><word id="294">a</word></unit></unit><unit type="Elaborator" id="910" unanalyzable="false" uncertain="false"><unit type="To Be Defined" id="297" unanalyzable="false" uncertain="false"><word id="296">level</word></unit></unit><unit type="Elaborator" id="911" unanalyzable="false" uncertain="false"><unit type="To Be Defined" id="299" unanalyzable="false" uncertain="false"><word id="298">playing</word></unit></unit><unit type="Center" id="916" unanalyzable="false" uncertain="false"><unit type="To Be Defined" id="301" unanalyzable="false" uncertain="false"><word id="300">field</word></unit></unit></unit></unit></unit></unit><unit type="Punctuation" id="303" unanalyzable="false" uncertain="false"><word id="302">,</word></unit><unit type="Punctuation" id="305" unanalyzable="false" uncertain="false"><word id="304">''</word></unit><unit type="Process" id="821" unanalyzable="false" uncertain="false"><unit type="To Be Defined" id="307" unanalyzable="false" uncertain="false"><word id="306">wrote</word></unit></unit><unit type="Participant" id="1138" unanalyzable="true" uncertain="false"><unit type="To Be Defined" id="309" unanalyzable="false" uncertain="false"><word id="308">Clyde</word></unit><unit type="To Be Defined" id="311" unanalyzable="false" uncertain="false"><word id="310">S.</word></unit><unit type="To Be Defined" id="313" unanalyzable="false" uncertain="false"><word id="312">McGregor</word></unit><unit type="To Be Defined" id="315" unanalyzable="false" uncertain="false"><word id="314">of</word></unit><unit type="To Be Defined" id="317" unanalyzable="false" uncertain="false"><word id="316">Winnetka</word></unit><unit type="Punctuation" id="319" unanalyzable="false" uncertain="false"><word id="318">,</word></unit><unit type="To Be Defined" id="321" unanalyzable="false" uncertain="false"><word id="320">Ill.</word></unit><unit type="Punctuation" id="323" unanalyzable="false" uncertain="false"><word id="322">,</word></unit></unit><unit type="Participant" id="823" unanalyzable="false" uncertain="false"><unit type="Relator" id="824" unanalyzable="false" uncertain="false"><unit type="To Be Defined" id="325" unanalyzable="false" uncertain="false"><word id="324">in</word></unit></unit><unit type="Elaborator" id="826" unanalyzable="false" uncertain="false"><unit type="Center" id="847" unanalyzable="false" uncertain="false"><unit type="To Be Defined" id="327" unanalyzable="false" uncertain="false"><word id="326">one</word></unit></unit><unit type="Relator" id="848" unanalyzable="false" uncertain="false"><unit type="To Be Defined" id="329" unanalyzable="false" uncertain="false"><word id="328">of</word></unit></unit></unit><unit type="Center" id="1139" unanalyzable="false" uncertain="false"><unit type="Elaborator" id="827" unanalyzable="false" uncertain="false"><unit type="To Be Defined" id="331" unanalyzable="false" uncertain="false"><word id="330">the</word></unit></unit><unit type="Elaborator" id="828" unanalyzable="false" uncertain="false"><unit type="To Be Defined" id="333" unanalyzable="false" uncertain="false"><word id="332">92</word></unit></unit><unit type="Center" id="829" unanalyzable="false" uncertain="false"><unit type="To Be Defined" id="335" unanalyzable="false" uncertain="false"><word id="334">letters</word></unit></unit></unit><unit type="Elaborator" id="830" unanalyzable="false" uncertain="false"><unit type="Parallel Scene" id="833" unanalyzable="false" uncertain="false"><remoteUnit id="829" type="Participant"></remoteUnit><unit type="Participant" id="831" unanalyzable="false" uncertain="false"><unit type="Elaborator" id="836" unanalyzable="false" uncertain="false"><unit type="To Be Defined" id="337" unanalyzable="false" uncertain="false"><word id="336">the</word></unit></unit><unit type="Center" id="837" unanalyzable="false" uncertain="false"><unit type="To Be Defined" id="339" unanalyzable="false" uncertain="false"><word id="338">agency</word></unit></unit></unit><unit type="Process" id="832" unanalyzable="false" uncertain="false"><unit type="Function" id="838" unanalyzable="false" uncertain="false"><unit type="To Be Defined" id="341" unanalyzable="false" uncertain="false"><word id="340">has</word></unit></unit><unit type="Center" id="839" unanalyzable="false" uncertain="false"><unit type="To Be Defined" id="343" unanalyzable="false" uncertain="false"><word id="342">received</word></unit></unit></unit></unit><unit type="Linker" id="834" unanalyzable="false" uncertain="false"><linkage args="833,835"></linkage><unit type="To Be Defined" id="345" unanalyzable="false" uncertain="false"><word id="344">since</word></unit></unit><unit type="Parallel Scene" id="835" unanalyzable="false" uncertain="false"><unit type="Participant" id="842" unanalyzable="false" uncertain="false"><unit type="Elaborator" id="840" unanalyzable="false" uncertain="false"><unit type="To Be Defined" id="347" unanalyzable="false" uncertain="false"><word id="346">the</word></unit></unit><unit type="Center" id="841" unanalyzable="false" uncertain="false"><unit type="To Be Defined" id="349" unanalyzable="false" uncertain="false"><word id="348">changes</word></unit></unit></unit><unit type="Process" id="843" unanalyzable="false" uncertain="false"><unit type="Function" id="845" unanalyzable="false" uncertain="false"><unit type="To Be Defined" id="351" unanalyzable="false" uncertain="false"><word id="350">were</word></unit></unit><unit type="Center" id="846" unanalyzable="false" uncertain="false"><unit type="To Be Defined" id="353" unanalyzable="false" uncertain="false"><word id="352">proposed</word></unit></unit></unit><unit type="aDverbial" id="844" unanalyzable="true" uncertain="false"><unit type="To Be Defined" id="355" unanalyzable="false" uncertain="false"><word id="354">Aug.</word></unit><unit type="To Be Defined" id="357" unanalyzable="false" uncertain="false"><word id="356">17</word></unit></unit></unit></unit></unit><unit type="Punctuation" id="359" unanalyzable="false" uncertain="false"><word id="358">.</word></unit></unit><unit type="Punctuation" id="361" unanalyzable="false" uncertain="false"><word id="360">``</word></unit><unit type="Parallel Scene" id="926" unanalyzable="false" uncertain="false"><unit type="Ground" id="918" unanalyzable="false" uncertain="false"><unit type="To Be Defined" id="363" unanalyzable="false" uncertain="false"><word id="362">Apparently</word></unit></unit><unit type="Participant" id="919" unanalyzable="false" uncertain="false"><unit type="Elaborator" id="927" unanalyzable="false" uncertain="false"><unit type="To Be Defined" id="365" unanalyzable="false" uncertain="false"><word id="364">the</word></unit></unit><unit type="Center" id="928" unanalyzable="false" uncertain="false"><unit type="To Be Defined" id="367" unanalyzable="false" uncertain="false"><word id="366">commission</word></unit></unit></unit><unit type="To Be Defined" id="920" unitGroupID="921" unanalyzable="false" uncertain="false"><unit type="Function" id="929" unanalyzable="false" uncertain="false"><unit type="To Be Defined" id="369" unanalyzable="false" uncertain="false"><word id="368">did</word></unit></unit></unit><unit type="aDverbial" id="923" unanalyzable="false" uncertain="false"><unit type="To Be Defined" id="371" unanalyzable="false" uncertain="false"><word id="370">not</word></unit></unit><unit type="aDverbial" id="924" unanalyzable="false" uncertain="false"><unit type="To Be Defined" id="373" unanalyzable="false" uncertain="false"><word id="372">really</word></unit></unit><unit type="To Be Defined" id="922" unitGroupID="921" unanalyzable="false" uncertain="false"><unit type="Center" id="930" unanalyzable="false" uncertain="false"><unit type="To Be Defined" id="375" unanalyzable="false" uncertain="false"><word id="374">believe</word></unit></unit></unit><unit type="Participant" id="925" unanalyzable="false" uncertain="false"><unit type="Relator" id="931" unanalyzable="false" uncertain="false"><unit type="To Be Defined" id="377" unanalyzable="false" uncertain="false"><word id="376">in</word></unit></unit><unit type="Elaborator" id="932" unanalyzable="false" uncertain="false"><unit type="To Be Defined" id="379" unanalyzable="false" uncertain="false"><word id="378">this</word></unit></unit><unit type="Center" id="933" unanalyzable="false" uncertain="false"><unit type="To Be Defined" id="381" unanalyzable="false" uncertain="false"><word id="380">ideal</word></unit></unit></unit></unit><unit type="Punctuation" id="383" unanalyzable="false" uncertain="false"><word id="382">.</word></unit><unit type="Punctuation" id="385" unanalyzable="false" uncertain="false"><word id="384">''</word></unit><unit type="Parallel Scene" id="955" unanalyzable="false" uncertain="false"><unit type="aDverbial" id="934" unanalyzable="false" uncertain="false"><unit type="To Be Defined" id="387" unanalyzable="false" uncertain="false"><word id="386">Currently</word></unit></unit><unit type="Punctuation" id="389" unanalyzable="false" uncertain="false"><word id="388">,</word></unit><unit type="Participant" id="935" unanalyzable="false" uncertain="false"><unit type="Elaborator" id="952" unanalyzable="false" uncertain="false"><unit type="To Be Defined" id="391" unanalyzable="false" uncertain="false"><word id="390">the</word></unit></unit><unit type="Center" id="953" unanalyzable="false" uncertain="false"><unit type="To Be Defined" id="393" unanalyzable="false" uncertain="false"><word id="392">rules</word></unit></unit></unit><unit type="To Be Defined" id="939" unitGroupID="940" unanalyzable="false" uncertain="false"><unit type="Elaborator" id="942" unanalyzable="false" uncertain="false"><unit type="To Be Defined" id="395" unanalyzable="false" uncertain="false"><word id="394">force</word></unit></unit></unit><unit type="Participant" id="938" unanalyzable="false" uncertain="false"><unit type="Center" id="945" unanalyzable="false" uncertain="false"><unit type="To Be Defined" id="397" unanalyzable="false" uncertain="false"><word id="396">executives</word></unit></unit><unit type="Punctuation" id="399" unanalyzable="false" uncertain="false"><word id="398">,</word></unit><unit type="Center" id="946" unanalyzable="false" uncertain="false"><unit type="To Be Defined" id="401" unanalyzable="false" uncertain="false"><word id="400">directors</word></unit></unit><unit type="Connector" id="947" unanalyzable="false" uncertain="false"><unit type="To Be Defined" id="403" unanalyzable="false" uncertain="false"><word id="402">and</word></unit></unit><unit type="Center" id="948" unanalyzable="false" uncertain="false"><unit type="Elaborator" id="949" unanalyzable="false" uncertain="false"><unit type="To Be Defined" id="405" unanalyzable="false" uncertain="false"><word id="404">other</word></unit></unit><unit type="Elaborator" id="950" unanalyzable="false" uncertain="false"><unit type="To Be Defined" id="407" unanalyzable="false" uncertain="false"><word id="406">corporate</word></unit></unit><unit type="Center" id="951" unanalyzable="false" uncertain="false"><unit type="To Be Defined" id="409" unanalyzable="false" uncertain="false"><word id="408">insiders</word></unit></unit></unit></unit><unit type="To Be Defined" id="941" unitGroupID="940" unanalyzable="false" uncertain="false"><unit type="Function" id="943" unanalyzable="false" uncertain="false"><unit type="To Be Defined" id="411" unanalyzable="false" uncertain="false"><word id="410">to</word></unit></unit><unit type="Center" id="944" unanalyzable="false" uncertain="false"><unit type="To Be Defined" id="413" unanalyzable="false" uncertain="false"><word id="412">report</word></unit></unit></unit><unit type="Participant" id="1140" unanalyzable="false" uncertain="false"><implicitUnit id="1141" type="Participant"></implicitUnit><unit type="Process" id="957" unanalyzable="false" uncertain="false"><unit type="Center" id="962" unanalyzable="false" uncertain="false"><unit type="To Be Defined" id="415" unanalyzable="false" uncertain="false"><word id="414">purchases</word></unit></unit><unit type="Connector" id="963" unanalyzable="false" uncertain="false"><unit type="To Be Defined" id="417" unanalyzable="false" uncertain="false"><word id="416">and</word></unit></unit><unit type="Center" id="964" unanalyzable="false" uncertain="false"><unit type="To Be Defined" id="419" unanalyzable="false" uncertain="false"><word id="418">sales</word></unit></unit></unit><unit type="Participant" id="956" unanalyzable="false" uncertain="false"><unit type="Relator" id="965" unanalyzable="false" uncertain="false"><unit type="To Be Defined" id="421" unanalyzable="false" uncertain="false"><word id="420">of</word></unit></unit><unit type="Elaborator" id="966" unanalyzable="false" uncertain="false"><unit type="Elaborator" id="968" unanalyzable="false" uncertain="false"><unit type="To Be Defined" id="423" unanalyzable="false" uncertain="false"><word id="422">their</word></unit></unit><unit type="Center" id="969" unanalyzable="false" uncertain="false"><unit type="To Be Defined" id="425" unanalyzable="false" uncertain="false"><word id="424">companies</word></unit></unit></unit><unit type="Punctuation" id="427" unanalyzable="false" uncertain="false"><word id="426">'</word></unit><unit type="Center" id="967" unanalyzable="false" uncertain="false"><unit type="To Be Defined" id="429" unanalyzable="false" uncertain="false"><word id="428">shares</word></unit></unit></unit></unit><unit type="aDverbial" id="974" unanalyzable="false" uncertain="false"><unit type="Center" id="976" unanalyzable="false" uncertain="false"><unit type="Relator" id="970" unanalyzable="false" uncertain="false"><unit type="To Be Defined" id="431" unanalyzable="false" uncertain="false"><word id="430">within</word></unit></unit><unit type="Elaborator" id="979" unanalyzable="false" uncertain="false"><unit type="To Be Defined" id="433" unanalyzable="false" uncertain="false"><word id="432">about</word></unit></unit><unit type="Center" id="980" unanalyzable="false" uncertain="false"><unit type="Elaborator" id="981" unanalyzable="false" uncertain="false"><unit type="To Be Defined" id="435" unanalyzable="false" uncertain="false"><word id="434">a</word></unit></unit><unit type="Center" id="982" unanalyzable="false" uncertain="false"><unit type="To Be Defined" id="437" unanalyzable="false" uncertain="false"><word id="436">month</word></unit></unit></unit></unit><unit type="Elaborator" id="977" unanalyzable="false" uncertain="false"><unit type="Relator" id="978" unanalyzable="false" uncertain="false"><unit type="To Be Defined" id="439" unanalyzable="false" uncertain="false"><word id="438">after</word></unit></unit><unit type="Elaborator" id="972" unanalyzable="false" uncertain="false"><unit type="To Be Defined" id="441" unanalyzable="false" uncertain="false"><word id="440">the</word></unit></unit><unit type="Center" id="973" unanalyzable="false" uncertain="false"><unit type="To Be Defined" id="443" unanalyzable="false" uncertain="false"><word id="442">transaction</word></unit></unit></unit></unit></unit><unit type="Punctuation" id="445" unanalyzable="false" uncertain="false"><word id="444">.</word></unit><unit type="Linker" id="983" unanalyzable="false" uncertain="false"><linkage args="955,1144"></linkage><unit type="To Be Defined" id="447" unanalyzable="false" uncertain="false"><word id="446">But</word></unit></unit><unit type="To Be Defined" id="1143" unitGroupID="1144" unanalyzable="false" uncertain="false"><unit type="Participant" id="1142" unanalyzable="false" uncertain="false"><unit type="Elaborator" id="1002" unanalyzable="false" uncertain="false"><unit type="Elaborator" id="1007" unanalyzable="false" uncertain="false"><unit type="To Be Defined" id="449" unanalyzable="false" uncertain="false"><word id="448">about</word></unit></unit><unit type="Center" id="1006" unanalyzable="true" uncertain="false"><unit type="To Be Defined" id="451" unanalyzable="false" uncertain="false"><word id="450">25</word></unit><unit type="Punctuation" id="453" unanalyzable="false" uncertain="false"><word id="452">%</word></unit></unit><unit type="Relator" id="1005" unanalyzable="false" uncertain="false"><unit type="To Be Defined" id="455" unanalyzable="false" uncertain="false"><word id="454">of</word></unit></unit></unit><unit type="Elaborator" id="1003" unanalyzable="false" uncertain="false"><unit type="To Be Defined" id="457" unanalyzable="false" uncertain="false"><word id="456">the</word></unit></unit><unit type="Center" id="1004" unanalyzable="false" uncertain="false"><unit type="To Be Defined" id="459" unanalyzable="false" uncertain="false"><word id="458">insiders</word></unit></unit></unit></unit><unit type="Punctuation" id="461" unanalyzable="false" uncertain="false"><word id="460">,</word></unit><unit type="Linker" id="998" unanalyzable="true" uncertain="false"><linkage args="1144,1146"></linkage><unit type="To Be Defined" id="463" unanalyzable="false" uncertain="false"><word id="462">according</word></unit><unit type="To Be Defined" id="465" unanalyzable="false" uncertain="false"><word id="464">to</word></unit></unit><unit type="Parallel Scene" id="1146" unanalyzable="false" uncertain="false"><implicitUnit id="1148" type="State"></implicitUnit><unit type="Participant" id="1147" unanalyzable="false" uncertain="false"><unit type="Elaborator" id="999" unanalyzable="false" uncertain="false"><unit type="To Be Defined" id="467" unanalyzable="false" uncertain="false"><word id="466">SEC</word></unit></unit><unit type="Center" id="1000" unanalyzable="false" uncertain="false"><unit type="To Be Defined" id="469" unanalyzable="false" uncertain="false"><word id="468">figures</word></unit></unit></unit></unit><unit type="Punctuation" id="471" unanalyzable="false" uncertain="false"><word id="470">,</word></unit><unit type="To Be Defined" id="1145" unitGroupID="1144" unanalyzable="false" uncertain="false"><unit type="Process" id="991" unanalyzable="false" uncertain="false"><unit type="To Be Defined" id="473" unanalyzable="false" uncertain="false"><word id="472">file</word></unit></unit><unit type="Participant" id="992" unanalyzable="false" uncertain="false"><unit type="Elaborator" id="995" unanalyzable="false" uncertain="false"><unit type="To Be Defined" id="475" unanalyzable="false" uncertain="false"><word id="474">their</word></unit></unit><unit type="Center" id="996" unanalyzable="false" uncertain="false"><unit type="To Be Defined" id="477" unanalyzable="false" uncertain="false"><word id="476">reports</word></unit></unit></unit><unit type="aDverbial" id="993" unanalyzable="false" uncertain="false"><unit type="To Be Defined" id="479" unanalyzable="false" uncertain="false"><word id="478">late</word></unit></unit></unit><unit type="Punctuation" id="481" unanalyzable="false" uncertain="false"><word id="480">.</word></unit><unit type="Parallel Scene" id="1072" unanalyzable="false" uncertain="false"><unit type="Participant" id="1155" unanalyzable="false" uncertain="false"><unit type="Parallel Scene" id="1015" unanalyzable="false" uncertain="false"><unit type="Participant" id="1012" unanalyzable="false" uncertain="false"><unit type="Elaborator" id="1022" unanalyzable="false" uncertain="false"><unit type="To Be Defined" id="483" unanalyzable="false" uncertain="false"><word id="482">The</word></unit></unit><unit type="Center" id="1023" unanalyzable="false" uncertain="false"><unit type="To Be Defined" id="485" unanalyzable="false" uncertain="false"><word id="484">changes</word></unit></unit></unit><unit type="Process" id="1013" unanalyzable="false" uncertain="false"><unit type="Function" id="1024" unanalyzable="false" uncertain="false"><unit type="To Be Defined" id="487" unanalyzable="false" uncertain="false"><word id="486">were</word></unit></unit><unit type="Center" id="1025" unanalyzable="false" uncertain="false"><unit type="To Be Defined" id="489" unanalyzable="false" uncertain="false"><word id="488">proposed</word></unit></unit></unit></unit><unit type="Linker" id="1014" unanalyzable="true" uncertain="false"><unit type="To Be Defined" id="491" unanalyzable="false" uncertain="false"><word id="490">in</word></unit><unit type="To Be Defined" id="493" unanalyzable="false" uncertain="false"><word id="492">an</word></unit><unit type="To Be Defined" id="495" unanalyzable="false" uncertain="false"><word id="494">effort</word></unit><unit type="To Be Defined" id="497" unanalyzable="false" uncertain="false"><word id="496">to</word></unit></unit><unit type="Parallel Scene" id="1016" unanalyzable="false" uncertain="false"><implicitUnit id="1070" type="Participant"></implicitUnit><unit type="Process" id="1026" unanalyzable="false" uncertain="false"><unit type="To Be Defined" id="499" unanalyzable="false" uncertain="false"><word id="498">streamline</word></unit></unit><unit type="Participant" id="1027" unanalyzable="false" uncertain="false"><unit type="Elaborator" id="1028" unanalyzable="false" uncertain="false"><unit type="To Be Defined" id="501" unanalyzable="false" uncertain="false"><word id="500">federal</word></unit></unit><unit type="Center" id="1029" unanalyzable="false" uncertain="false"><unit type="To Be Defined" id="503" unanalyzable="false" uncertain="false"><word id="502">bureaucracy</word></unit></unit></unit></unit><unit type="Linker" id="1017" unanalyzable="false" uncertain="false"><unit type="To Be Defined" id="505" unanalyzable="false" uncertain="false"><word id="504">and</word></unit></unit><unit type="Parallel Scene" id="1154" unanalyzable="false" uncertain="false"><unit type="Process" id="1032" unanalyzable="false" uncertain="false"><unit type="Elaborator" id="1030" unanalyzable="false" uncertain="false"><unit type="To Be Defined" id="507" unanalyzable="false" uncertain="false"><word id="506">boost</word></unit></unit><unit type="Center" id="1033" unanalyzable="false" uncertain="false"><unit type="To Be Defined" id="509" unanalyzable="false" uncertain="false"><word id="508">compliance</word></unit></unit></unit><unit type="Participant" id="1149" unanalyzable="false" uncertain="false"><unit type="Relator" id="1056" unanalyzable="false" uncertain="false"><unit type="To Be Defined" id="511" unanalyzable="false" uncertain="false"><word id="510">by</word></unit></unit><unit type="Elaborator" id="1057" unanalyzable="false" uncertain="false"><unit type="To Be Defined" id="513" unanalyzable="false" uncertain="false"><word id="512">the</word></unit></unit><unit type="Center" id="1058" unanalyzable="false" uncertain="false"><unit type="To Be Defined" id="515" unanalyzable="false" uncertain="false"><word id="514">executives</word></unit></unit><unit type="Punctuation" id="517" unanalyzable="false" uncertain="false"><word id="516">``</word></unit><unit type="Elaborator" id="1059" unanalyzable="false" uncertain="false"><remoteUnit id="1058" type="Participant"></remoteUnit><unit type="Relator" id="1060" unanalyzable="false" uncertain="false"><unit type="To Be Defined" id="519" unanalyzable="false" uncertain="false"><word id="518">who</word></unit></unit><unit type="To Be Defined" id="1062" unitGroupID="1063" unanalyzable="false" uncertain="false"><unit type="Function" id="1068" unanalyzable="false" uncertain="false"><unit type="To Be Defined" id="521" unanalyzable="false" uncertain="false"><word id="520">are</word></unit></unit></unit><unit type="aDverbial" id="1061" unanalyzable="false" uncertain="false"><unit type="To Be Defined" id="523" unanalyzable="false" uncertain="false"><word id="522">really</word></unit></unit><unit type="To Be Defined" id="1064" unitGroupID="1063" unanalyzable="false" uncertain="false"><unit type="Center" id="1069" unanalyzable="false" uncertain="false"><unit type="To Be Defined" id="525" unanalyzable="false" uncertain="false"><word id="524">calling</word></unit></unit></unit><unit type="Participant" id="1065" unanalyzable="false" uncertain="false"><unit type="Elaborator" id="1066" unanalyzable="false" uncertain="false"><unit type="To Be Defined" id="527" unanalyzable="false" uncertain="false"><word id="526">the</word></unit></unit><unit type="Center" id="1067" unanalyzable="false" uncertain="false"><unit type="To Be Defined" id="529" unanalyzable="false" uncertain="false"><word id="528">shots</word></unit></unit></unit></unit></unit></unit></unit><unit type="Punctuation" id="531" unanalyzable="false" uncertain="false"><word id="530">,</word></unit><unit type="Punctuation" id="533" unanalyzable="false" uncertain="false"><word id="532">''</word></unit><unit type="Process" id="1020" unanalyzable="false" uncertain="false"><unit type="To Be Defined" id="535" unanalyzable="false" uncertain="false"><word id="534">said</word></unit></unit><unit type="Participant" id="1021" unanalyzable="false" uncertain="false"><unit type="Center" id="1034" unanalyzable="true" uncertain="false"><unit type="To Be Defined" id="537" unanalyzable="false" uncertain="false"><word id="536">Brian</word></unit><unit type="To Be Defined" id="539" unanalyzable="false" uncertain="false"><word id="538">Lane</word></unit></unit><unit type="Punctuation" id="541" unanalyzable="false" uncertain="false"><word id="540">,</word></unit><unit type="Elaborator" id="1133" unanalyzable="false" uncertain="false"><unit type="Elaborator" id="1037" unanalyzable="false" uncertain="false"><unit type="To Be Defined" id="543" unanalyzable="false" uncertain="false"><word id="542">special</word></unit></unit><unit type="Center" id="1038" unanalyzable="false" uncertain="false"><unit type="To Be Defined" id="545" unanalyzable="false" uncertain="false"><word id="544">counsel</word></unit></unit><unit type="Elaborator" id="1132" unanalyzable="false" uncertain="false"><unit type="Relator" id="1040" unanalyzable="false" uncertain="false"><unit type="To Be Defined" id="547" unanalyzable="false" uncertain="false"><word id="546">at</word></unit></unit><unit type="Elaborator" id="1041" unanalyzable="false" uncertain="false"><unit type="To Be Defined" id="549" unanalyzable="false" uncertain="false"><word id="548">the</word></unit></unit><unit type="Elaborator" id="1042" unanalyzable="false" uncertain="false"><unit type="Center" id="1050" unanalyzable="false" uncertain="false"><unit type="To Be Defined" id="551" unanalyzable="false" uncertain="false"><word id="550">SEC</word></unit></unit><unit type="Relator" id="1049" unanalyzable="false" uncertain="false"><unit type="To Be Defined" id="553" unanalyzable="false" uncertain="false"><word id="552">'s</word></unit></unit></unit><unit type="Center" id="1043" unanalyzable="false" uncertain="false"><unit type="To Be Defined" id="555" unanalyzable="false" uncertain="false"><word id="554">office</word></unit></unit><unit type="Elaborator" id="1045" unanalyzable="false" uncertain="false"><unit type="Relator" id="1046" unanalyzable="false" uncertain="false"><unit type="To Be Defined" id="557" unanalyzable="false" uncertain="false"><word id="556">of</word></unit></unit><unit type="Elaborator" id="1047" unanalyzable="false" uncertain="false"><unit type="To Be Defined" id="559" unanalyzable="false" uncertain="false"><word id="558">disclosure</word></unit></unit><unit type="Center" id="1048" unanalyzable="false" uncertain="false"><unit type="To Be Defined" id="561" unanalyzable="false" uncertain="false"><word id="560">policy</word></unit></unit></unit><unit type="Punctuation" id="563" unanalyzable="false" uncertain="false"><word id="562">,</word></unit><unit type="Elaborator" id="1131" unanalyzable="false" uncertain="false"><remoteUnit id="1043" type="Participant"></remoteUnit><unit type="Relator" id="1051" unanalyzable="false" uncertain="false"><unit type="To Be Defined" id="565" unanalyzable="false" uncertain="false"><word id="564">which</word></unit></unit><unit type="Process" id="1052" unanalyzable="false" uncertain="false"><unit type="To Be Defined" id="567" unanalyzable="false" uncertain="false"><word id="566">proposed</word></unit></unit><unit type="Participant" id="1053" unanalyzable="false" uncertain="false"><unit type="Elaborator" id="1054" unanalyzable="false" uncertain="false"><unit type="To Be Defined" id="569" unanalyzable="false" uncertain="false"><word id="568">the</word></unit></unit><unit type="Center" id="1055" unanalyzable="false" uncertain="false"><unit type="To Be Defined" id="571" unanalyzable="false" uncertain="false"><word id="570">changes</word></unit></unit></unit></unit></unit></unit></unit></unit><unit type="Punctuation" id="573" unanalyzable="false" uncertain="false"><word id="572">.</word></unit><unit type="Parallel Scene" id="1071" unanalyzable="false" uncertain="false"><unit type="Participant" id="1097" unanalyzable="false" uncertain="false"><unit type="Parallel Scene" id="1128" unanalyzable="false" uncertain="false"><unit type="Participant" id="1074" unanalyzable="false" uncertain="false"><unit type="Center" id="1073" unanalyzable="false" uncertain="false"><unit type="To Be Defined" id="575" unanalyzable="false" uncertain="false"><word id="574">Investors</word></unit></unit><unit type="Punctuation" id="577" unanalyzable="false" uncertain="false"><word id="576">,</word></unit><unit type="Center" id="1084" unanalyzable="false" uncertain="false"><unit type="Elaborator" id="1087" unanalyzable="false" uncertain="false"><unit type="To Be Defined" id="579" unanalyzable="false" uncertain="false"><word id="578">money</word></unit></unit><unit type="Center" id="1088" unanalyzable="false" uncertain="false"><unit type="To Be Defined" id="581" unanalyzable="false" uncertain="false"><word id="580">managers</word></unit></unit></unit><unit type="Connector" id="1086" unanalyzable="false" uncertain="false"><unit type="To Be Defined" id="583" unanalyzable="false" uncertain="false"><word id="582">and</word></unit></unit><unit type="Center" id="1085" unanalyzable="false" uncertain="false"><unit type="Elaborator" id="1089" unanalyzable="false" uncertain="false"><unit type="To Be Defined" id="585" unanalyzable="false" uncertain="false"><word id="584">corporate</word></unit></unit><unit type="Center" id="1090" unanalyzable="false" uncertain="false"><unit type="To Be Defined" id="587" unanalyzable="false" uncertain="false"><word id="586">officials</word></unit></unit></unit></unit><unit type="To Be Defined" id="1075" unitGroupID="1076" unanalyzable="false" uncertain="false"><unit type="Function" id="1081" unanalyzable="false" uncertain="false"><unit type="To Be Defined" id="589" unanalyzable="false" uncertain="false"><word id="588">had</word></unit></unit></unit><unit type="aDverbial" id="1078" unanalyzable="false" uncertain="false"><unit type="Elaborator" id="1079" unanalyzable="false" uncertain="false"><unit type="To Be Defined" id="591" unanalyzable="false" uncertain="false"><word id="590">until</word></unit></unit><unit type="Center" id="1080" unanalyzable="false" uncertain="false"><unit type="To Be Defined" id="593" unanalyzable="false" uncertain="false"><word id="592">today</word></unit></unit></unit><unit type="To Be Defined" id="1077" unitGroupID="1076" unanalyzable="false" uncertain="false"><unit type="Function" id="1082" unanalyzable="false" uncertain="false"><unit type="To Be Defined" id="595" unanalyzable="false" uncertain="false"><word id="594">to</word></unit></unit><unit type="Center" id="1083" unanalyzable="false" uncertain="false"><unit type="To Be Defined" id="597" unanalyzable="false" uncertain="false"><word id="596">comment</word></unit></unit></unit><unit type="Participant" id="1091" unanalyzable="false" uncertain="false"><unit type="Relator" id="1100" unanalyzable="false" uncertain="false"><unit type="To Be Defined" id="599" unanalyzable="false" uncertain="false"><word id="598">on</word></unit></unit><unit type="Elaborator" id="1101" unanalyzable="false" uncertain="false"><unit type="To Be Defined" id="601" unanalyzable="false" uncertain="false"><word id="600">the</word></unit></unit><unit type="Center" id="1102" unanalyzable="false" uncertain="false"><unit type="To Be Defined" id="603" unanalyzable="false" uncertain="false"><word id="602">proposals</word></unit></unit></unit></unit><unit type="Punctuation" id="605" unanalyzable="false" uncertain="false"><word id="604">,</word></unit><unit type="Linker" id="1093" unanalyzable="false" uncertain="false"><unit type="To Be Defined" id="607" unanalyzable="false" uncertain="false"><word id="606">and</word></unit></unit><unit type="Parallel Scene" id="1150" unanalyzable="false" uncertain="false"><unit type="Participant" id="1103" unanalyzable="false" uncertain="false"><unit type="Elaborator" id="1115" unanalyzable="false" uncertain="false"><unit type="To Be Defined" id="609" unanalyzable="false" uncertain="false"><word id="608">the</word></unit></unit><unit type="Center" id="1116" unanalyzable="false" uncertain="false"><unit type="To Be Defined" id="611" unanalyzable="false" uncertain="false"><word id="610">issue</word></unit></unit></unit><unit type="Process" id="1104" unanalyzable="false" uncertain="false"><unit type="Function" id="1113" unanalyzable="false" uncertain="false"><unit type="To Be Defined" id="613" unanalyzable="false" uncertain="false"><word id="612">has</word></unit></unit><unit type="Center" id="1114" unanalyzable="false" uncertain="false"><unit type="To Be Defined" id="615" unanalyzable="false" uncertain="false"><word id="614">produced</word></unit></unit></unit><unit type="Participant" id="1151" unanalyzable="false" uncertain="false"><unit type="Elaborator" id="1117" unanalyzable="false" uncertain="false"><unit type="To Be Defined" id="617" unanalyzable="false" uncertain="false"><word id="616">more</word></unit></unit><unit type="Center" id="1105" unanalyzable="false" uncertain="false"><unit type="To Be Defined" id="619" unanalyzable="false" uncertain="false"><word id="618">mail</word></unit></unit><unit type="Elaborator" id="1152" unanalyzable="false" uncertain="false"><remoteUnit id="1104" type="Process"></remoteUnit><unit type="Relator" id="1118" unanalyzable="false" uncertain="false"><unit type="To Be Defined" id="621" unanalyzable="false" uncertain="false"><word id="620">than</word></unit></unit><unit type="Participant" id="1127" unanalyzable="false" uncertain="false"><unit type="Elaborator" id="1119" unanalyzable="false" uncertain="false"><unit type="Elaborator" id="1124" unanalyzable="false" uncertain="false"><unit type="To Be Defined" id="623" unanalyzable="false" uncertain="false"><word id="622">almost</word></unit></unit><unit type="Elaborator" id="1125" unanalyzable="false" uncertain="false"><unit type="To Be Defined" id="625" unanalyzable="false" uncertain="false"><word id="624">any</word></unit></unit><unit type="Center" id="1126" unanalyzable="false" uncertain="false"><unit type="To Be Defined" id="627" unanalyzable="false" uncertain="false"><word id="626">other</word></unit></unit></unit><unit type="Center" id="1120" unanalyzable="false" uncertain="false"><unit type="To Be Defined" id="629" unanalyzable="false" uncertain="false"><word id="628">issue</word></unit></unit><unit type="Elaborator" id="1121" unanalyzable="false" uncertain="false"><unit type="Relator" id="1122" unanalyzable="false" uncertain="false"><unit type="To Be Defined" id="631" unanalyzable="false" uncertain="false"><word id="630">in</word></unit></unit><unit type="Center" id="1123" unanalyzable="false" uncertain="false"><unit type="To Be Defined" id="633" unanalyzable="false" uncertain="false"><word id="632">memory</word></unit></unit></unit></unit></unit></unit></unit></unit><unit type="Punctuation" id="635" unanalyzable="false" uncertain="false"><word id="634">,</word></unit><unit type="Participant" id="1095" unanalyzable="false" uncertain="false"><unit type="Elaborator" id="1098" unanalyzable="false" uncertain="false"><unit type="To Be Defined" id="637" unanalyzable="false" uncertain="false"><word id="636">Mr.</word></unit></unit><unit type="Center" id="1099" unanalyzable="false" uncertain="false"><unit type="To Be Defined" id="639" unanalyzable="false" uncertain="false"><word id="638">Lane</word></unit></unit></unit><unit type="Process" id="1096" unanalyzable="false" uncertain="false"><unit type="To Be Defined" id="641" unanalyzable="false" uncertain="false"><word id="640">said</word></unit></unit></unit><unit type="Punctuation" id="643" unanalyzable="false" uncertain="false"><word id="642">.</word></unit></unit></unit></units><LRUunits><LRUunit id="1133"></LRUunit><LRUunit id="1132"></LRUunit><LRUunit id="1131"></LRUunit><LRUunit id="1128"></LRUunit><LRUunit id="1127"></LRUunit><LRUunit id="1126"></LRUunit><LRUunit id="1125"></LRUunit><LRUunit id="1124"></LRUunit><LRUunit id="1123"></LRUunit><LRUunit id="1122"></LRUunit><LRUunit id="1121"></LRUunit><LRUunit id="1120"></LRUunit><LRUunit id="1119"></LRUunit><LRUunit id="1118"></LRUunit><LRUunit id="1117"></LRUunit><LRUunit id="1116"></LRUunit><LRUunit id="1115"></LRUunit><LRUunit id="1114"></LRUunit><LRUunit id="1113"></LRUunit><LRUunit id="1105"></LRUunit><LRUunit id="1104"></LRUunit><LRUunit id="1103"></LRUunit><LRUunit id="1102"></LRUunit><LRUunit id="1101"></LRUunit><LRUunit id="1100"></LRUunit><LRUunit id="1099"></LRUunit><LRUunit id="1098"></LRUunit><LRUunit id="1097"></LRUunit><LRUunit id="1096"></LRUunit><LRUunit id="1095"></LRUunit><LRUunit id="1093"></LRUunit><LRUunit id="1091"></LRUunit><LRUunit id="1090"></LRUunit><LRUunit id="1089"></LRUunit><LRUunit id="1088"></LRUunit><LRUunit id="1087"></LRUunit><LRUunit id="1086"></LRUunit><LRUunit id="1085"></LRUunit><LRUunit id="1084"></LRUunit><LRUunit id="1083"></LRUunit><LRUunit id="1082"></LRUunit><LRUunit id="1081"></LRUunit><LRUunit id="1080"></LRUunit><LRUunit id="1079"></LRUunit><LRUunit id="1078"></LRUunit><LRUunit id="1076"></LRUunit><LRUunit id="1074"></LRUunit><LRUunit id="1073"></LRUunit><LRUunit id="1072"></LRUunit><LRUunit id="1071"></LRUunit><LRUunit id="1069"></LRUunit><LRUunit id="1068"></LRUunit><LRUunit id="1067"></LRUunit><LRUunit id="1066"></LRUunit><LRUunit id="1065"></LRUunit><LRUunit id="1063"></LRUunit><LRUunit id="1061"></LRUunit><LRUunit id="1060"></LRUunit><LRUunit id="1059"></LRUunit><LRUunit id="1058"></LRUunit><LRUunit id="1057"></LRUunit><LRUunit id="1056"></LRUunit><LRUunit id="1055"></LRUunit><LRUunit id="1054"></LRUunit><LRUunit id="1053"></LRUunit><LRUunit id="1052"></LRUunit><LRUunit id="1051"></LRUunit><LRUunit id="1050"></LRUunit><LRUunit id="1049"></LRUunit><LRUunit id="1048"></LRUunit><LRUunit id="1047"></LRUunit><LRUunit id="1046"></LRUunit><LRUunit id="1045"></LRUunit><LRUunit id="1043"></LRUunit><LRUunit id="1042"></LRUunit><LRUunit id="1041"></LRUunit><LRUunit id="1040"></LRUunit><LRUunit id="1038"></LRUunit><LRUunit id="1037"></LRUunit><LRUunit id="1034"></LRUunit><LRUunit id="1033"></LRUunit><LRUunit id="1032"></LRUunit><LRUunit id="1030"></LRUunit><LRUunit id="1029"></LRUunit><LRUunit id="1028"></LRUunit><LRUunit id="1027"></LRUunit><LRUunit id="1026"></LRUunit><LRUunit id="1025"></LRUunit><LRUunit id="1024"></LRUunit><LRUunit id="1023"></LRUunit><LRUunit id="1022"></LRUunit><LRUunit id="1021"></LRUunit><LRUunit id="1020"></LRUunit><LRUunit id="1017"></LRUunit><LRUunit id="1016"></LRUunit><LRUunit id="1015"></LRUunit><LRUunit id="1014"></LRUunit><LRUunit id="1013"></LRUunit><LRUunit id="1012"></LRUunit><LRUunit id="1007"></LRUunit><LRUunit id="1006"></LRUunit><LRUunit id="1005"></LRUunit><LRUunit id="1004"></LRUunit><LRUunit id="1003"></LRUunit><LRUunit id="1002"></LRUunit><LRUunit id="1000"></LRUunit><LRUunit id="999"></LRUunit><LRUunit id="998"></LRUunit><LRUunit id="996"></LRUunit><LRUunit id="995"></LRUunit><LRUunit id="993"></LRUunit><LRUunit id="992"></LRUunit><LRUunit id="991"></LRUunit><LRUunit id="983"></LRUunit><LRUunit id="982"></LRUunit><LRUunit id="981"></LRUunit><LRUunit id="980"></LRUunit><LRUunit id="979"></LRUunit><LRUunit id="978"></LRUunit><LRUunit id="977"></LRUunit><LRUunit id="976"></LRUunit><LRUunit id="974"></LRUunit><LRUunit id="973"></LRUunit><LRUunit id="972"></LRUunit><LRUunit id="970"></LRUunit><LRUunit id="969"></LRUunit><LRUunit id="968"></LRUunit><LRUunit id="967"></LRUunit><LRUunit id="966"></LRUunit><LRUunit id="965"></LRUunit><LRUunit id="964"></LRUunit><LRUunit id="963"></LRUunit><LRUunit id="962"></LRUunit><LRUunit id="957"></LRUunit><LRUunit id="956"></LRUunit><LRUunit id="955"></LRUunit><LRUunit id="953"></LRUunit><LRUunit id="952"></LRUunit><LRUunit id="951"></LRUunit><LRUunit id="950"></LRUunit><LRUunit id="949"></LRUunit><LRUunit id="948"></LRUunit><LRUunit id="947"></LRUunit><LRUunit id="946"></LRUunit><LRUunit id="945"></LRUunit><LRUunit id="944"></LRUunit><LRUunit id="943"></LRUunit><LRUunit id="942"></LRUunit><LRUunit id="940"></LRUunit><LRUunit id="938"></LRUunit><LRUunit id="935"></LRUunit><LRUunit id="934"></LRUunit><LRUunit id="933"></LRUunit><LRUunit id="932"></LRUunit><LRUunit id="931"></LRUunit><LRUunit id="930"></LRUunit><LRUunit id="929"></LRUunit><LRUunit id="928"></LRUunit><LRUunit id="927"></LRUunit><LRUunit id="926"></LRUunit><LRUunit id="925"></LRUunit><LRUunit id="924"></LRUunit><LRUunit id="923"></LRUunit><LRUunit id="921"></LRUunit><LRUunit id="919"></LRUunit><LRUunit id="918"></LRUunit><LRUunit id="917"></LRUunit><LRUunit id="916"></LRUunit><LRUunit id="915"></LRUunit><LRUunit id="911"></LRUunit><LRUunit id="910"></LRUunit><LRUunit id="909"></LRUunit><LRUunit id="908"></LRUunit><LRUunit id="906"></LRUunit><LRUunit id="905"></LRUunit><LRUunit id="904"></LRUunit><LRUunit id="903"></LRUunit><LRUunit id="902"></LRUunit><LRUunit id="901"></LRUunit><LRUunit id="900"></LRUunit><LRUunit id="899"></LRUunit><LRUunit id="898"></LRUunit><LRUunit id="897"></LRUunit><LRUunit id="896"></LRUunit><LRUunit id="895"></LRUunit><LRUunit id="894"></LRUunit><LRUunit id="893"></LRUunit><LRUunit id="892"></LRUunit><LRUunit id="891"></LRUunit><LRUunit id="890"></LRUunit><LRUunit id="887"></LRUunit><LRUunit id="884"></LRUunit><LRUunit id="883"></LRUunit><LRUunit id="882"></LRUunit><LRUunit id="881"></LRUunit><LRUunit id="880"></LRUunit><LRUunit id="879"></LRUunit><LRUunit id="878"></LRUunit><LRUunit id="877"></LRUunit><LRUunit id="876"></LRUunit><LRUunit id="875"></LRUunit><LRUunit id="874"></LRUunit><LRUunit id="871"></LRUunit><LRUunit id="869"></LRUunit><LRUunit id="868"></LRUunit><LRUunit id="867"></LRUunit><LRUunit id="866"></LRUunit><LRUunit id="865"></LRUunit><LRUunit id="864"></LRUunit><LRUunit id="863"></LRUunit><LRUunit id="862"></LRUunit><LRUunit id="861"></LRUunit><LRUunit id="860"></LRUunit><LRUunit id="859"></LRUunit><LRUunit id="857"></LRUunit><LRUunit id="856"></LRUunit><LRUunit id="855"></LRUunit><LRUunit id="854"></LRUunit><LRUunit id="853"></LRUunit><LRUunit id="852"></LRUunit><LRUunit id="850"></LRUunit><LRUunit id="644"></LRUunit><LRUunit id="645"></LRUunit><LRUunit id="646"></LRUunit><LRUunit id="647"></LRUunit><LRUunit id="648"></LRUunit><LRUunit id="650"></LRUunit><LRUunit id="651"></LRUunit><LRUunit id="652"></LRUunit><LRUunit id="653"></LRUunit><LRUunit id="654"></LRUunit><LRUunit id="655"></LRUunit><LRUunit id="656"></LRUunit><LRUunit id="657"></LRUunit><LRUunit id="658"></LRUunit><LRUunit id="659"></LRUunit><LRUunit id="660"></LRUunit><LRUunit id="661"></LRUunit><LRUunit id="662"></LRUunit><LRUunit id="663"></LRUunit><LRUunit id="664"></LRUunit><LRUunit id="665"></LRUunit><LRUunit id="666"></LRUunit><LRUunit id="667"></LRUunit><LRUunit id="668"></LRUunit><LRUunit id="670"></LRUunit><LRUunit id="671"></LRUunit><LRUunit id="673"></LRUunit><LRUunit id="674"></LRUunit><LRUunit id="675"></LRUunit><LRUunit id="676"></LRUunit><LRUunit id="677"></LRUunit><LRUunit id="678"></LRUunit><LRUunit id="679"></LRUunit><LRUunit id="680"></LRUunit><LRUunit id="681"></LRUunit><LRUunit id="682"></LRUunit><LRUunit id="683"></LRUunit><LRUunit id="684"></LRUunit><LRUunit id="685"></LRUunit><LRUunit id="686"></LRUunit><LRUunit id="687"></LRUunit><LRUunit id="688"></LRUunit><LRUunit id="689"></LRUunit><LRUunit id="690"></LRUunit><LRUunit id="691"></LRUunit><LRUunit id="692"></LRUunit><LRUunit id="693"></LRUunit><LRUunit id="694"></LRUunit><LRUunit id="695"></LRUunit><LRUunit id="696"></LRUunit><LRUunit id="698"></LRUunit><LRUunit id="699"></LRUunit><LRUunit id="700"></LRUunit><LRUunit id="701"></LRUunit><LRUunit id="703"></LRUunit><LRUunit id="704"></LRUunit><LRUunit id="705"></LRUunit><LRUunit id="707"></LRUunit><LRUunit id="708"></LRUunit><LRUunit id="709"></LRUunit><LRUunit id="710"></LRUunit><LRUunit id="711"></LRUunit><LRUunit id="712"></LRUunit><LRUunit id="713"></LRUunit><LRUunit id="714"></LRUunit><LRUunit id="715"></LRUunit><LRUunit id="716"></LRUunit><LRUunit id="718"></LRUunit><LRUunit id="719"></LRUunit><LRUunit id="720"></LRUunit><LRUunit id="721"></LRUunit><LRUunit id="722"></LRUunit><LRUunit id="723"></LRUunit><LRUunit id="724"></LRUunit><LRUunit id="725"></LRUunit><LRUunit id="726"></LRUunit><LRUunit id="727"></LRUunit><LRUunit id="728"></LRUunit><LRUunit id="729"></LRUunit><LRUunit id="730"></LRUunit><LRUunit id="731"></LRUunit><LRUunit id="732"></LRUunit><LRUunit id="733"></LRUunit><LRUunit id="734"></LRUunit><LRUunit id="735"></LRUunit><LRUunit id="736"></LRUunit><LRUunit id="737"></LRUunit><LRUunit id="738"></LRUunit><LRUunit id="739"></LRUunit><LRUunit id="740"></LRUunit><LRUunit id="741"></LRUunit><LRUunit id="743"></LRUunit><LRUunit id="745"></LRUunit><LRUunit id="747"></LRUunit><LRUunit id="749"></LRUunit><LRUunit id="754"></LRUunit><LRUunit id="755"></LRUunit><LRUunit id="756"></LRUunit><LRUunit id="757"></LRUunit><LRUunit id="758"></LRUunit><LRUunit id="759"></LRUunit><LRUunit id="760"></LRUunit><LRUunit id="761"></LRUunit><LRUunit id="762"></LRUunit><LRUunit id="763"></LRUunit><LRUunit id="764"></LRUunit><LRUunit id="765"></LRUunit><LRUunit id="766"></LRUunit><LRUunit id="768"></LRUunit><LRUunit id="771"></LRUunit><LRUunit id="774"></LRUunit><LRUunit id="775"></LRUunit><LRUunit id="776"></LRUunit><LRUunit id="778"></LRUunit><LRUunit id="779"></LRUunit><LRUunit id="780"></LRUunit><LRUunit id="781"></LRUunit><LRUunit id="782"></LRUunit><LRUunit id="783"></LRUunit><LRUunit id="784"></LRUunit><LRUunit id="785"></LRUunit><LRUunit id="786"></LRUunit><LRUunit id="787"></LRUunit><LRUunit id="788"></LRUunit><LRUunit id="790"></LRUunit><LRUunit id="791"></LRUunit><LRUunit id="792"></LRUunit><LRUunit id="794"></LRUunit><LRUunit id="795"></LRUunit><LRUunit id="796"></LRUunit><LRUunit id="797"></LRUunit><LRUunit id="798"></LRUunit><LRUunit id="799"></LRUunit><LRUunit id="800"></LRUunit><LRUunit id="801"></LRUunit><LRUunit id="802"></LRUunit><LRUunit id="803"></LRUunit><LRUunit id="804"></LRUunit><LRUunit id="805"></LRUunit><LRUunit id="806"></LRUunit><LRUunit id="807"></LRUunit><LRUunit id="808"></LRUunit><LRUunit id="809"></LRUunit><LRUunit id="810"></LRUunit><LRUunit id="811"></LRUunit><LRUunit id="815"></LRUunit><LRUunit id="817"></LRUunit><LRUunit id="819"></LRUunit><LRUunit id="820"></LRUunit><LRUunit id="821"></LRUunit><LRUunit id="823"></LRUunit><LRUunit id="824"></LRUunit><LRUunit id="826"></LRUunit><LRUunit id="827"></LRUunit><LRUunit id="828"></LRUunit><LRUunit id="829"></LRUunit><LRUunit id="830"></LRUunit><LRUunit id="831"></LRUunit><LRUunit id="832"></LRUunit><LRUunit id="833"></LRUunit><LRUunit id="834"></LRUunit><LRUunit id="835"></LRUunit><LRUunit id="836"></LRUunit><LRUunit id="837"></LRUunit><LRUunit id="838"></LRUunit><LRUunit id="839"></LRUunit><LRUunit id="840"></LRUunit><LRUunit id="841"></LRUunit><LRUunit id="842"></LRUunit><LRUunit id="843"></LRUunit><LRUunit id="844"></LRUunit><LRUunit id="845"></LRUunit><LRUunit id="846"></LRUunit><LRUunit id="847"></LRUunit><LRUunit id="848"></LRUunit><LRUunit id="1129"></LRUunit><LRUunit id="1130"></LRUunit><LRUunit id="1134"></LRUunit><LRUunit id="1135"></LRUunit><LRUunit id="1136"></LRUunit><LRUunit id="1137"></LRUunit><LRUunit id="1138"></LRUunit><LRUunit id="1139"></LRUunit><LRUunit id="1140"></LRUunit><LRUunit id="1142"></LRUunit><LRUunit id="1144"></LRUunit><LRUunit id="1146"></LRUunit><LRUunit id="1147"></LRUunit><LRUunit id="1149"></LRUunit><LRUunit id="1150"></LRUunit><LRUunit id="1151"></LRUunit><LRUunit id="1152"></LRUunit><LRUunit id="1154"></LRUunit><LRUunit id="1155"></LRUunit></LRUunits><hiddenUnits><hiddenUnit id="690"></hiddenUnit><hiddenUnit id="703"></hiddenUnit><hiddenUnit id="710"></hiddenUnit><hiddenUnit id="731"></hiddenUnit><hiddenUnit id="810"></hiddenUnit><hiddenUnit id="926"></hiddenUnit><hiddenUnit id="955"></hiddenUnit><hiddenUnit id="983"></hiddenUnit><hiddenUnit id="998"></hiddenUnit><hiddenUnit id="1071"></hiddenUnit><hiddenUnit id="1144"></hiddenUnit><hiddenUnit id="1146"></hiddenUnit></hiddenUnits></root>